longtrainer/__init__.py
longtrainer/bot.py
longtrainer/loaders.py
longtrainer/retrieval.py
longtrainer/trainer.py
longtrainer/utils.py
longtrainer/vision_bot.py
longtrainer-0.3.4.dist-info/LICENSE
longtrainer-0.3.4.dist-info/METADATA
longtrainer-0.3.4.dist-info/WHEEL
longtrainer-0.3.4.dist-info/top_level.txt
longtrainer-0.3.4.dist-info/RECORD
