Metadata-Version: 2.1
Name: longtrainer
Version: 0.3.4
Summary: Production Ready LangChain
Home-page: https://github.com/ENDEVSOLS/Long-Trainer
Author: Endevsols
Author-email: technology@endevsols.com
Classifier: Programming Language :: Python :: 3
Classifier: License :: OSI Approved :: MIT License
Classifier: Operating System :: OS Independent
License-File: LICENSE
Requires-Dist: langchain-core ==0.3.17
Requires-Dist: openai ==1.57.4
Requires-Dist: faiss-cpu ==1.9.0
Requires-Dist: tiktoken ==0.8.0
Requires-Dist: wikipedia ==1.4.0
Requires-Dist: langchain ==0.3.0
Requires-Dist: youtube-transcript-api ==0.6.2
Requires-Dist: pytube ==15.0.0
Requires-Dist: pypdf ==5.1.0
Requires-Dist: docx2txt ==0.8
Requires-Dist: fastapi ==0.115.5
Requires-Dist: uvicorn ==0.32.0
Requires-Dist: pydantic ==2.9.2
Requires-Dist: pandas ==2.2.3
Requires-Dist: pymongo ==4.10.1
Requires-Dist: python-docx ==1.1.2
Requires-Dist: langchain-openai ==0.2.8
Requires-Dist: langchain-community ==0.3.0
Requires-Dist: cryptography ==43.0.3
Requires-Dist: duckduckgo-search ==6.3.5
Requires-Dist: python-magic ==0.4.27
Requires-Dist: unstructured ==0.15.7
Requires-Dist: unstructured[all-docs]
Requires-Dist: langchain-unstructured[local]
